gitpushagent/__init__.py
gitpushagent/git_operations.py
gitpushagent-0.1.2.dist-info/licenses/LICENSE
gitpushagent-0.1.2.dist-info/METADATA
gitpushagent-0.1.2.dist-info/WHEEL
gitpushagent-0.1.2.dist-info/entry_points.txt
gitpushagent-0.1.2.dist-info/top_level.txt
gitpushagent-0.1.2.dist-info/RECORD
